{
  "@context": "https://schema.org",
  "@type": "Review",
  "author": {
    "@type": "Person",
    "name": "Anonymous"
  },
  "reviewBody": "Chris provided the most first class services when I was panicked during the water damage in my house. He came out right away, was very professional and knowledgeable, and helped me through the entire process with the insurance company. He provided reasonable prices and I highly recommend him.",
  "reviewRating": {
    "@type": "Rating",
    "ratingValue": 5,
    "bestRating": 5
  },
  "itemReviewed": {
    "@type": "Organization",
    "name": "First To Respond Restoration",
    "url": "http://first2respond.com/",
    "makesOffer": {
      "@type": "Offer",
      "itemOffered": {
        "@type": "Service",
        "name": "Water Damage Restoration"
      }
    }
  }
}